pyblp/__init__.py
pyblp/construction.py
pyblp/exceptions.py
pyblp/micro.py
pyblp/options.py
pyblp/parameters.py
pyblp/primitives.py
pyblp/version.py
pyblp/configurations/__init__.py
pyblp/configurations/formulation.py
pyblp/configurations/integration.py
pyblp/configurations/iteration.py
pyblp/configurations/optimization.py
pyblp/data/__init__.py
pyblp/data/blp_agents.csv
pyblp/data/blp_products.csv
pyblp/data/nevo_agents.csv
pyblp/data/nevo_products.csv
pyblp/data/petrin_agents.csv
pyblp/data/petrin_covariances.csv
pyblp/data/petrin_products.csv
pyblp/data/petrin_values.csv
pyblp/economies/__init__.py
pyblp/economies/economy.py
pyblp/economies/problem.py
pyblp/economies/simulation.py
pyblp/markets/__init__.py
pyblp/markets/economy_results_market.py
pyblp/markets/market.py
pyblp/markets/problem_market.py
pyblp/markets/simulation_market.py
pyblp/results/__init__.py
pyblp/results/bootstrapped_results.py
pyblp/results/economy_results.py
pyblp/results/importance_sampling_results.py
pyblp/results/optimal_instrument_results.py
pyblp/results/problem_results.py
pyblp/results/simulation_results.py
pyblp/utilities/__init__.py
pyblp/utilities/algebra.py
pyblp/utilities/basics.py
pyblp/utilities/statistics.py
tests/__init__.py
tests/conftest.py
tests/test_blp.py
tests/test_formulation.py
tests/test_integration.py
tests/test_iteration.py
tests/test_optimization.py
pyblp-1.1.2.dist-info/LICENSE.txt
pyblp-1.1.2.dist-info/METADATA
pyblp-1.1.2.dist-info/WHEEL
pyblp-1.1.2.dist-info/top_level.txt
pyblp-1.1.2.dist-info/RECORD
