Metadata-Version: 2.1
Name: pyblp
Version: 1.1.2
Summary: BLP demand estimation with Python 3
Home-page: https://github.com/jeffgortmaker/pyblp
Author: Jeff Gortmaker, Christopher Conlon
Author-email: jeff@jeffgortmaker.com
License: MIT
Project-URL: Documentation, http://pyblp.readthedocs.io/en/latest
Project-URL: Tracker, https://github.com/jeffgortmaker/pyblp/issues
Platform: UNKNOWN
Classifier: Development Status :: 4 - Beta
Classifier: Intended Audience :: Science/Research
Classifier: License :: OSI Approved :: MIT License
Classifier: Operating System :: OS Independent
Classifier: Programming Language :: Python
Classifier: Programming Language :: Python :: 3
Classifier: Programming Language :: Python :: 3.6
Classifier: Programming Language :: Python :: 3.7
Classifier: Programming Language :: Python :: 3.8
Classifier: Programming Language :: Python :: 3.9
Classifier: Topic :: Scientific/Engineering
Requires-Python: >=3.6
License-File: LICENSE.txt
Requires-Dist: numpy (>=1.17.0)
Requires-Dist: patsy (>=0.5.1)
Requires-Dist: pyhdfe (>=0.1.0)
Requires-Dist: scipy (>=1.2.0)
Requires-Dist: sympy (>=1.1.0)
Provides-Extra: docs
Requires-Dist: sphinx (==2.0.0) ; extra == 'docs'
Requires-Dist: pandas ; extra == 'docs'
Requires-Dist: ipython ; extra == 'docs'
Requires-Dist: matplotlib ; extra == 'docs'
Requires-Dist: astunparse ; extra == 'docs'
Requires-Dist: sphinx-rtd-theme (==0.4.3) ; extra == 'docs'
Requires-Dist: nbsphinx (==0.5.0) ; extra == 'docs'
Requires-Dist: jinja2 (~=2.11) ; extra == 'docs'
Requires-Dist: docutils (==0.17) ; extra == 'docs'
Requires-Dist: sphinxcontrib-googleanalytics (==0.4) ; extra == 'docs'
Provides-Extra: tests
Requires-Dist: pytest ; extra == 'tests'
Requires-Dist: pytest-xdist ; extra == 'tests'
Requires-Dist: linearmodels ; extra == 'tests'
Requires-Dist: dill ; extra == 'tests'
Requires-Dist: pathos ; extra == 'tests'
